git_gq/__init__.py
git_gq/git_gq.py
git_gq/doc/LICENSE
git_gq/doc/README.rst
git_gq/doc/html/backups.html
git_gq/doc/html/commandline.html
git_gq/doc/html/conflicts.html
git_gq/doc/html/examples.html
git_gq/doc/html/genindex.html
git_gq/doc/html/implementation.html
git_gq/doc/html/index.html
git_gq/doc/html/install.html
git_gq/doc/html/license.html
git_gq/doc/html/objects.inv
git_gq/doc/html/overview.html
git_gq/doc/html/prerequisites.html
git_gq/doc/html/search.html
git_gq/doc/html/searchindex.js
git_gq/doc/html/_sources/backups.rst.txt
git_gq/doc/html/_sources/commandline.rst.txt
git_gq/doc/html/_sources/conflicts.rst.txt
git_gq/doc/html/_sources/examples.rst.txt
git_gq/doc/html/_sources/implementation.rst.txt
git_gq/doc/html/_sources/index.rst.txt
git_gq/doc/html/_sources/install.rst.txt
git_gq/doc/html/_sources/license.rst.txt
git_gq/doc/html/_sources/overview.rst.txt
git_gq/doc/html/_sources/prerequisites.rst.txt
git_gq/doc/html/_static/_sphinx_javascript_frameworks_compat.js
git_gq/doc/html/_static/basic.css
git_gq/doc/html/_static/doctools.js
git_gq/doc/html/_static/documentation_options.js
git_gq/doc/html/_static/file.png
git_gq/doc/html/_static/jquery.js
git_gq/doc/html/_static/language_data.js
git_gq/doc/html/_static/minus.png
git_gq/doc/html/_static/plus.png
git_gq/doc/html/_static/pygments.css
git_gq/doc/html/_static/searchtools.js
git_gq/doc/html/_static/sphinx_highlight.js
git_gq/doc/html/_static/css/badge_only.css
git_gq/doc/html/_static/css/theme.css
git_gq/doc/html/_static/css/fonts/Roboto-Slab-Bold.woff
git_gq/doc/html/_static/css/fonts/Roboto-Slab-Bold.woff2
git_gq/doc/html/_static/css/fonts/Roboto-Slab-Regular.woff
git_gq/doc/html/_static/css/fonts/Roboto-Slab-Regular.woff2
git_gq/doc/html/_static/css/fonts/fontawesome-webfont.eot
git_gq/doc/html/_static/css/fonts/fontawesome-webfont.svg
git_gq/doc/html/_static/css/fonts/fontawesome-webfont.ttf
git_gq/doc/html/_static/css/fonts/fontawesome-webfont.woff
git_gq-2.1.dist-info/licenses/LICENSE
git_gq-2.1.dist-info/METADATA
git_gq-2.1.dist-info/WHEEL
git_gq-2.1.dist-info/entry_points.txt
git_gq-2.1.dist-info/top_level.txt
git_gq-2.1.dist-info/RECORD
